LICENSE
README.md
setup.py
placeholder/__init__.py
placeholder/placeholder.py
pyplaceholder.egg-info/PKG-INFO
pyplaceholder.egg-info/SOURCES.txt
pyplaceholder.egg-info/dependency_links.txt
pyplaceholder.egg-info/top_level.txt
test/test_placeholders.py