Metadata-Version: 2.1
Name: pyplaceholder
Version: 0.0.4
Summary: A placeholder detector in text or in text files
Home-page: https://github.com/jmgomezsoriano/pyplaceholder
Author: José Manuel Gómez Soriano
Author-email: jmgomez.soriano@gmail.com
License: LGPL v3
Platform: UNKNOWN
Classifier: Programming Language :: Python :: 3
Classifier: License :: OSI Approved :: GNU General Public License v3 (GPLv3)
Classifier: Operating System :: OS Independent
Requires-Python: >=3.6
